README
setup.py
SanicMongo/__init__.py
SanicMongo/clients.py
SanicMongo/connection.py
SanicMongo/core.py
SanicMongo/decorators.py
SanicMongo/dereference.py
SanicMongo/document.py
SanicMongo/exceptions.py
SanicMongo/fields.py
SanicMongo/gridfs.py
SanicMongo/metaprogramming.py
SanicMongo/monkey.py
SanicMongo/queryset.py
SanicMongo/utils.py
SanicMongo.egg-info/PKG-INFO
SanicMongo.egg-info/SOURCES.txt
SanicMongo.egg-info/dependency_links.txt
SanicMongo.egg-info/requires.txt
SanicMongo.egg-info/top_level.txt