Metadata-Version: 1.1
Name: SanicMongo
Version: 0.9.4.post1
Summary: MongoMotor: An async document-object mapper for MongoDB
Home-page: http://mongomotor.poraodojuca.net/
Author: BeePaste
Author-email: hi@beepaste.io
License: UNKNOWN
Platform: UNKNOWN
Classifier: Development Status :: 3 - Alpha
Classifier: Intended Audience :: Developers
Classifier: License :: OSI Approved :: GNU General Public License (GPL)
Classifier: Natural Language :: English
Classifier: Operating System :: OS Independent
Classifier: Programming Language :: Python :: 3
Classifier: Programming Language :: Python :: 3.4
Classifier: Topic :: Software Development :: Libraries :: Python Modules
Provides: SanicMongo
